{
  "POIs": [
    {
      "fit": [
        2.1595263481140137,
        2.2079367637634277,
        2.2580506801605225
      ],
      "name": "r"
    }
  ],
  "method": "default",
  "params": [
    {
      "fit": [
        1.28212308883667,
        1.28212308883667,
        1.28212308883667
      ],
      "groups": [],
      "impact_r": 2.7418136596679688e-05,
      "name": "WGammaBkgPhotonSF",
      "prefit": [
        0.0,
        0.0,
        0.0
      ],
      "r": [
        2.2079641819000244,
        2.2079367637634277,
        2.2079641819000244
      ],
      "type": "Unconstrained"
    },
    {
      "fit": [
        0.9480006694793701,
        0.9480006694793701,
        0.9480006694793701
      ],
      "groups": [],
      "impact_r": 2.7418136596679688e-05,
      "name": "ZGammaBkgPhotonSF",
      "prefit": [
        0.0,
        0.0,
        0.0
      ],
      "r": [
        2.2079641819000244,
        2.2079367637634277,
        2.2079641819000244
      ],
      "type": "Unconstrained"
    },
    {
      "fit": [
        -1.5291619300842285,
        -1.2970240116119385,
        -1.0638766288757324
      ],
      "groups": [],
      "impact_r": 0.001359701156616211,
      "name": "prop_bineleJets_bin0",
      "prefit": [
        -0.9999999999999999,
        0.0,
        0.9999999999999999
      ],
      "r": [
        2.2065682411193848,
        2.207927942276001,
        2.209071159362793
      ],
      "type": "Gaussian"
    },
    {
      "fit": [
        -0.9446945190429688,
        -0.7077733874320984,
        -0.4698551595211029
      ],
      "groups": [],
      "impact_r": 0.0012333393096923828,
      "name": "prop_bineleJets_bin1",
      "prefit": [
        -0.9999999999999999,
        0.0,
        0.9999999999999999
      ],
      "r": [
        2.20672869682312,
        2.207939863204956,
        2.2091732025146484
      ],
      "type": "Gaussian"
    },
    {
      "fit": [
        -1.1109458208084106,
        -0.5458095073699951,
        0.024096224457025528
      ],
      "groups": [],
      "impact_r": 0.031164169311523438,
      "name": "prop_bineleJets_bin10",
      "prefit": [
        -0.9999999999999999,
        0.0,
        0.9999999999999999
      ],
      "r": [
        2.2391462326049805,
        2.207982063293457,
        2.1776139736175537
      ],
      "type": "Gaussian"
    },
    {
      "fit": [
        -1.166048288345337,
        -0.6707073450088501,
        -0.16559532284736633
      ],
      "groups": [],
      "impact_r": 0.020417213439941406,
      "name": "prop_bineleJets_bin11",
      "prefit": [
        -0.9999999999999999,
        0.0,
        0.9999999999999999
      ],
      "r": [
        2.228350877761841,
        2.2079336643218994,
        2.187930107116699
      ],
      "type": "Gaussian"
    },
    {
      "fit": [
        0.26484811305999756,
        0.734744668006897,
        1.212559700012207
      ],
      "groups": [],
      "impact_r": 0.013022661209106445,
      "name": "prop_bineleJets_bin12",
      "prefit": [
        -0.9999999999999999,
        0.0,
        0.9999999999999999
      ],
      "r": [
        2.2209413051605225,
        2.207918643951416,
        2.195160388946533
      ],
      "type": "Gaussian"
    },
    {
      "fit": [
        -0.4468036890029907,
        -0.16140514612197876,
        0.1302686333656311
      ],
      "groups": [],
      "impact_r": 0.007807016372680664,
      "name": "prop_bineleJets_bin13",
      "prefit": [
        -0.9999999999999999,
        0.0,
        0.9999999999999999
      ],
      "r": [
        2.215743064880371,
        2.2079360485076904,
        2.2005300521850586
      ],
      "type": "Gaussian"
    },
    {
      "fit": [
        -0.6170346140861511,
        -0.25770723819732666,
        0.10505948215723038
      ],
      "groups": [],
      "impact_r": 0.006657838821411133,
      "name": "prop_bineleJets_bin14",
      "prefit": [
        -0.9999999999999999,
        0.0,
        0.9999999999999999
      ],
      "r": [
        2.2145683765411377,
        2.2079105377197266,
        2.2014474868774414
      ],
      "type": "Gaussian"
    },
    {
      "fit": [
        -0.413169264793396,
        0.11281339079141617,
        0.6414356231689453
      ],
      "groups": [],
      "impact_r": 0.0018794536590576172,
      "name": "prop_bineleJets_bin15",
      "prefit": [
        -0.9999999999999999,
        0.0,
        0.9999999999999999
      ],
      "r": [
        2.209782838821411,
        2.2079358100891113,
        2.2060563564300537
      ],
      "type": "Gaussian"
    },
    {
      "fit": [
        0.06023401767015457,
        0.43624481558799744,
        0.8168845176696777
      ],
      "groups": [],
      "impact_r": 0.0008399486541748047,
      "name": "prop_bineleJets_bin16",
      "prefit": [
        -0.9999999999999999,
        0.0,
        0.9999999999999999
      ],
      "r": [
        2.2071266174316406,
        2.2079408168792725,
        2.2087807655334473
      ],
      "type": "Gaussian"
    },
    {
      "fit": [
        -0.921571671962738,
        -0.5619993805885315,
        -0.1976778209209442
      ],
      "groups": [],
      "impact_r": 0.0009257793426513672,
      "name": "prop_bineleJets_bin17",
      "prefit": [
        -0.9999999999999999,
        0.0,
        0.9999999999999999
      ],
      "r": [
        2.207014560699463,
        2.2079315185546875,
        2.208857297897339
      ],
      "type": "Gaussian"
    },
    {
      "fit": [
        1.8369706869125366,
        2.4075164794921875,
        2.987665891647339
      ],
      "groups": [],
      "impact_r": 0.0006830692291259766,
      "name": "prop_bineleJets_bin18",
      "prefit": [
        -0.9999999999999999,
        0.0,
        0.9999999999999999
      ],
      "r": [
        2.207317352294922,
        2.208000421524048,
        2.2085959911346436
      ],
      "type": "Gaussian"
    },
    {
      "fit": [
        -0.7846781611442566,
        -0.5143256187438965,
        -0.23837123811244965
      ],
      "groups": [],
      "impact_r": 0.0007953643798828125,
      "name": "prop_bineleJets_bin19",
      "prefit": [
        -0.9999999999999999,
        0.0,
        0.9999999999999999
      ],
      "r": [
        2.207139730453491,
        2.207935094833374,
        2.2087302207946777
      ],
      "type": "Gaussian"
    },
    {
      "fit": [
        -0.5480958223342896,
        -0.0790562704205513,
        0.3934527337551117
      ],
      "groups": [],
      "impact_r": 0.0002951622009277344,
      "name": "prop_bineleJets_bin2",
      "prefit": [
        -0.9999999999999999,
        0.0,
        0.9999999999999999
      ],
      "r": [
        2.2080917358398438,
        2.208125352859497,
        2.2078301906585693
      ],
      "type": "Gaussian"
    },
    {
      "fit": [
        -2.0609138011932373,
        -1.7325791120529175,
        -1.4021689891815186
      ],
      "groups": [],
      "impact_r": 0.004573822021484375,
      "name": "prop_bineleJets_bin3",
      "prefit": [
        -0.9999999999999999,
        0.0,
        0.9999999999999999
      ],
      "r": [
        2.2124338150024414,
        2.207859992980957,
        2.2035248279571533
      ],
      "type": "Gaussian"
    },
    {
      "fit": [
        -0.6028963923454285,
        -0.14486661553382874,
        0.31955355405807495
      ],
      "groups": [],
      "impact_r": 0.008682489395141602,
      "name": "prop_bineleJets_bin4",
      "prefit": [
        -0.9999999999999999,
        0.0,
        0.9999999999999999
      ],
      "r": [
        2.216596841812134,
        2.207914352416992,
        2.1993470191955566
      ],
      "type": "Gaussian"
    },
    {
      "fit": [
        -1.3481694459915161,
        -1.0068501234054565,
        -0.6599874496459961
      ],
      "groups": [],
      "impact_r": 0.013696908950805664,
      "name": "prop_bineleJets_bin5",
      "prefit": [
        -0.9999999999999999,
        0.0,
        0.9999999999999999
      ],
      "r": [
        2.2216320037841797,
        2.207935094833374,
        2.1947245597839355
      ],
      "type": "Gaussian"
    },
    {
      "fit": [
        -1.4159409999847412,
        -0.931265652179718,
        -0.44225725531578064
      ],
      "groups": [],
      "impact_r": 0.019349336624145508,
      "name": "prop_bineleJets_bin6",
      "prefit": [
        -0.9999999999999999,
        0.0,
        0.9999999999999999
      ],
      "r": [
        2.2272894382476807,
        2.207940101623535,
        2.1889326572418213
      ],
      "type": "Gaussian"
    },
    {
      "fit": [
        -0.6709616780281067,
        -0.14723534882068634,
        0.38287657499313354
      ],
      "groups": [],
      "impact_r": 0.027710676193237305,
      "name": "prop_bineleJets_bin7",
      "prefit": [
        -0.9999999999999999,
        0.0,
        0.9999999999999999
      ],
      "r": [
        2.235649585723877,
        2.2079389095306396,
        2.1810243129730225
      ],
      "type": "Gaussian"
    },
    {
      "fit": [
        0.2221759408712387,
        0.8745157122612,
        1.5360052585601807
      ],
      "groups": [],
      "impact_r": 0.03421425819396973,
      "name": "prop_bineleJets_bin8",
      "prefit": [
        -0.9999999999999999,
        0.0,
        0.9999999999999999
      ],
      "r": [
        2.242217779159546,
        2.208003520965576,
        2.1746373176574707
      ],
      "type": "Gaussian"
    },
    {
      "fit": [
        -0.21138353645801544,
        0.45301976799964905,
        1.1227666139602661
      ],
      "groups": [],
      "impact_r": 0.03615307807922363,
      "name": "prop_bineleJets_bin9",
      "prefit": [
        -0.9999999999999999,
        0.0,
        0.9999999999999999
      ],
      "r": [
        2.244035005569458,
        2.2078819274902344,
        2.1729323863983154
      ],
      "type": "Gaussian"
    },
    {
      "fit": [
        -1.0317946672439575,
        -0.4687471091747284,
        0.09570854157209396
      ],
      "groups": [],
      "impact_r": 0.003501415252685547,
      "name": "prop_binmuJets_bin0",
      "prefit": [
        -0.9999999999999999,
        0.0,
        0.9999999999999999
      ],
      "r": [
        2.204493522644043,
        2.2079949378967285,
        2.211453676223755
      ],
      "type": "Gaussian"
    },
    {
      "fit": [
        -0.8429585695266724,
        -0.27192363142967224,
        0.29592859745025635
      ],
      "groups": [],
      "impact_r": 0.0033826828002929688,
      "name": "prop_binmuJets_bin1",
      "prefit": [
        -0.9999999999999999,
        0.0,
        0.9999999999999999
      ],
      "r": [
        2.204728126525879,
        2.207888603210449,
        2.211271286010742
      ],
      "type": "Gaussian"
    },
    {
      "fit": [
        0.059259288012981415,
        0.6475886106491089,
        1.2436516284942627
      ],
      "groups": [],
      "impact_r": 0.0017745494842529297,
      "name": "prop_binmuJets_bin10",
      "prefit": [
        -0.9999999999999999,
        0.0,
        0.9999999999999999
      ],
      "r": [
        2.20627498626709,
        2.2080495357513428,
        2.2097201347351074
      ],
      "type": "Gaussian"
    },
    {
      "fit": [
        -1.3473812341690063,
        -1.1594876050949097,
        -0.9724125266075134
      ],
      "groups": [],
      "impact_r": 0.002125263214111328,
      "name": "prop_binmuJets_bin11",
      "prefit": [
        -0.9999999999999999,
        0.0,
        0.9999999999999999
      ],
      "r": [
        2.205803632736206,
        2.2079288959503174,
        2.2100441455841064
      ],
      "type": "Gaussian"
    },
    {
      "fit": [
        -1.282879114151001,
        -0.616445779800415,
        0.05139905959367752
      ],
      "groups": [],
      "impact_r": 0.003225564956665039,
      "name": "prop_binmuJets_bin2",
      "prefit": [
        -0.9999999999999999,
        0.0,
        0.9999999999999999
      ],
      "r": [
        2.2047841548919678,
        2.2079343795776367,
        2.2111599445343018
      ],
      "type": "Gaussian"
    },
    {
      "fit": [
        -0.48178744316101074,
        -0.04180009663105011,
        0.397073358297348
      ],
      "groups": [],
      "impact_r": 0.003373384475708008,
      "name": "prop_binmuJets_bin3",
      "prefit": [
        -0.9999999999999999,
        0.0,
        0.9999999999999999
      ],
      "r": [
        2.2046256065368652,
        2.2079460620880127,
        2.2113194465637207
      ],
      "type": "Gaussian"
    },
    {
      "fit": [
        0.9789379239082336,
        1.6867129802703857,
        2.4015085697174072
      ],
      "groups": [],
      "impact_r": 0.003340005874633789,
      "name": "prop_binmuJets_bin4",
      "prefit": [
        -0.9999999999999999,
        0.0,
        0.9999999999999999
      ],
      "r": [
        2.2048542499542236,
        2.2081942558288574,
        2.211246967315674
      ],
      "type": "Gaussian"
    },
    {
      "fit": [
        0.7656112909317017,
        1.390256404876709,
        2.025998115539551
      ],
      "groups": [],
      "impact_r": 0.0028007030487060547,
      "name": "prop_binmuJets_bin5",
      "prefit": [
        -0.9999999999999999,
        0.0,
        0.9999999999999999
      ],
      "r": [
        2.205287456512451,
        2.2078628540039062,
        2.2106635570526123
      ],
      "type": "Gaussian"
    },
    {
      "fit": [
        -1.7498526573181152,
        -1.3695461750030518,
        -0.9847971200942993
      ],
      "groups": [],
      "impact_r": 0.002433300018310547,
      "name": "prop_binmuJets_bin6",
      "prefit": [
        -0.9999999999999999,
        0.0,
        0.9999999999999999
      ],
      "r": [
        2.2055423259735107,
        2.207918643951416,
        2.2103519439697266
      ],
      "type": "Gaussian"
    },
    {
      "fit": [
        -1.9891698360443115,
        -1.4405272006988525,
        -0.881492555141449
      ],
      "groups": [],
      "impact_r": 0.0024073123931884766,
      "name": "prop_binmuJets_bin7",
      "prefit": [
        -0.9999999999999999,
        0.0,
        0.9999999999999999
      ],
      "r": [
        2.2056384086608887,
        2.2079107761383057,
        2.210318088531494
      ],
      "type": "Gaussian"
    },
    {
      "fit": [
        -0.6183626651763916,
        -0.3142309784889221,
        -0.010526301339268684
      ],
      "groups": [],
      "impact_r": 0.0022144317626953125,
      "name": "prop_binmuJets_bin8",
      "prefit": [
        -0.9999999999999999,
        0.0,
        0.9999999999999999
      ],
      "r": [
        2.2057220935821533,
        2.207930564880371,
        2.2101449966430664
      ],
      "type": "Gaussian"
    },
    {
      "fit": [
        -1.2231130599975586,
        -0.6439775824546814,
        -0.05484415218234062
      ],
      "groups": [],
      "impact_r": 0.0020520687103271484,
      "name": "prop_binmuJets_bin9",
      "prefit": [
        -0.9999999999999999,
        0.0,
        0.9999999999999999
      ],
      "r": [
        2.205986738204956,
        2.208038806915283,
        2.209998369216919
      ],
      "type": "Gaussian"
    }
  ]
}